prtx_faq/__init__.py
prtx_faq/apps.py
prtx_faq/forms.py
prtx_faq/models.py
prtx_faq/prtx.py
prtx_faq/signals.py
prtx_faq/urls.py
prtx_faq/views.py
prtx_faq/locale/django.pot
prtx_faq/locale/ar/LC_MESSAGES/django.mo
prtx_faq/locale/ar/LC_MESSAGES/django.po
prtx_faq/locale/ca/LC_MESSAGES/django.mo
prtx_faq/locale/ca/LC_MESSAGES/django.po
prtx_faq/locale/cs/LC_MESSAGES/django.mo
prtx_faq/locale/cs/LC_MESSAGES/django.po
prtx_faq/locale/d/LC_MESSAGES/django.mo
prtx_faq/locale/d/LC_MESSAGES/django.po
prtx_faq/locale/de/LC_MESSAGES/django.mo
prtx_faq/locale/de/LC_MESSAGES/django.po
prtx_faq/locale/de_DE/LC_MESSAGES/django.mo
prtx_faq/locale/de_DE/LC_MESSAGES/django.po
prtx_faq/locale/de_Formal/LC_MESSAGES/django.mo
prtx_faq/locale/de_Formal/LC_MESSAGES/django.po
prtx_faq/locale/de_Informal/LC_MESSAGES/django.mo
prtx_faq/locale/de_Informal/LC_MESSAGES/django.po
prtx_faq/locale/e/LC_MESSAGES/django.mo
prtx_faq/locale/e/LC_MESSAGES/django.po
prtx_faq/locale/el/LC_MESSAGES/django.mo
prtx_faq/locale/el/LC_MESSAGES/django.po
prtx_faq/locale/en_Mozilla/LC_MESSAGES/django.mo
prtx_faq/locale/en_Mozilla/LC_MESSAGES/django.po
prtx_faq/locale/es/LC_MESSAGES/django.mo
prtx_faq/locale/es/LC_MESSAGES/django.po
prtx_faq/locale/es_MX/LC_MESSAGES/django.mo
prtx_faq/locale/es_MX/LC_MESSAGES/django.po
prtx_faq/locale/fr_FR/LC_MESSAGES/django.mo
prtx_faq/locale/fr_FR/LC_MESSAGES/django.po
prtx_faq/locale/id/LC_MESSAGES/django.mo
prtx_faq/locale/id/LC_MESSAGES/django.po
prtx_faq/locale/it/LC_MESSAGES/django.mo
prtx_faq/locale/it/LC_MESSAGES/django.po
prtx_faq/locale/ja_JP/LC_MESSAGES/django.mo
prtx_faq/locale/ja_JP/LC_MESSAGES/django.po
prtx_faq/locale/pt_BR/LC_MESSAGES/django.mo
prtx_faq/locale/pt_BR/LC_MESSAGES/django.po
prtx_faq/locale/pt_PT/LC_MESSAGES/django.mo
prtx_faq/locale/pt_PT/LC_MESSAGES/django.po
prtx_faq/locale/zh_CN/LC_MESSAGES/django.mo
prtx_faq/locale/zh_CN/LC_MESSAGES/django.po
prtx_faq/locale/zh_Hant/LC_MESSAGES/django.mo
prtx_faq/locale/zh_Hant/LC_MESSAGES/django.po
prtx_faq-1.0.3.dist-info/LICENSE
prtx_faq-1.0.3.dist-info/METADATA
prtx_faq-1.0.3.dist-info/WHEEL
prtx_faq-1.0.3.dist-info/entry_points.txt
prtx_faq-1.0.3.dist-info/top_level.txt
prtx_faq-1.0.3.dist-info/RECORD
