Metadata-Version: 2.1
Name: prtx-faq
Version: 1.0.3
Summary: An FAQ plugin for pretalx and pretix
Home-page: https://github.com/pretalx/prtx-faq
Author: Tobias Kunze
Author-email: r@rixx.de
License: Apache Software License
License-File: LICENSE
